[{"title":"Async（nodejs）实战","createDate":"2015-05-29","urlTitle":"2015-05-29-translate-nodejs-async-in-practice","url":"data/2015-05-29-translate-nodejs-async-in-practice.json"},{"title":"理解进程替换（Process Substitution）","createDate":"2015-05-25","urlTitle":"2015-05-25-understand-process-subsitution","url":"data/2015-05-25-understand-process-subsitution.json"},{"title":"使用bats对bash代码进行测试","createDate":"2015-05-21","urlTitle":"2015-05-21-use-bats","url":"data/2015-05-21-use-bats.json"},{"title":"编写命令创建github博客文章","createDate":"2015-05-20","urlTitle":"2015-05-20-bash-script-to-create-post","url":"data/2015-05-20-bash-script-to-create-post.json"},{"title":"使用httpie代替curl和wget","createDate":"2015-05-18","urlTitle":"2015-05-18-use-httpie","url":"data/2015-05-18-use-httpie.json"},{"title":"简历","createDate":"2015-05-14","urlTitle":"2015-05-14-aboutme","url":"data/2015-05-14-aboutme.json"},{"title":"USE标记（翻译）","createDate":"2015-04-21","urlTitle":"2015-04-21-gentoo-trans-01","url":"data/2015-04-21-gentoo-trans-01.json"}]